yt2text/__init__.py
yt2text/yt2text.py
yt2text-1.0.2.dist-info/METADATA
yt2text-1.0.2.dist-info/WHEEL
yt2text-1.0.2.dist-info/top_level.txt
yt2text-1.0.2.dist-info/RECORD
