Metadata-Version: 2.1
Name: yt2text
Version: 1.0.2
Summary: Extract text from a YouTube video in a single command, using OpenAi's Whisper speech recognition model
Home-page: https://github.com/atahanuz/yt2text
Author: Atahan Uz
Author-email: atahanuz23@gmail.com
Classifier: Programming Language :: Python :: 3
Classifier: License :: OSI Approved :: MIT License
Classifier: Operating System :: OS Independent
Requires-Dist: numpy
Requires-Dist: ffmpeg
Requires-Dist: whisper
